<?xml version="1.0" encoding="UTF-8"?>
<beans xmlns="http://www.springframework.org/schema/beans"
       xmlns:xsi="http://www.w3.org/2001/XMLSchema-instance"
       xmlns:util="http://www.springframework.org/schema/util" xsi:schemaLocation="
        http://www.springframework.org/schema/beans http://www.springframework.org/schema/beans/spring-beans.xsd
        http://www.springframework.org/schema/util http://www.springframework.org/schema/util/spring-util.xsd"> <!-- bean definitions here -->
    <bean id="dao" class="com.mainapp3.DAO" > </bean>
    <bean id="service" class="com.mainapp3.Service">
        <property name="dao" ref="dao"/>
    </bean>
    <bean id="controller" class="com.mainapp3.Controller">
        <property name="service" ref="service"/>
    </bean>


</beans>